srtm/__init__.py
srtm/srtm.py
srtm_dl-0.0.5.dist-info/LICENSE
srtm_dl-0.0.5.dist-info/METADATA
srtm_dl-0.0.5.dist-info/WHEEL
srtm_dl-0.0.5.dist-info/top_level.txt
srtm_dl-0.0.5.dist-info/RECORD
