Metadata-Version: 2.1
Name: srtm-dl
Version: 0.0.5
Summary: A Python library (multi-threaded) for retrieving SRTM elevation map of CGIAR-CSI
Author-email: Ghasem Abdi <ghasem.abdi@yahoo.com>
License: MIT License        
Project-URL: Homepage, https://github.com/Abdi-Ghasem/srtmDownloader
Project-URL: Bug Tracker, https://github.com/Abdi-Ghasem/srtmDownloader/issues
Classifier: Programming Language :: Python :: 3
Classifier: License :: OSI Approved :: MIT License
Classifier: Operating System :: OS Independent
Requires-Python: >=3.9
License-File: LICENSE
Requires-Dist: numpy
Requires-Dist: pyproj
Requires-Dist: rasterio
